nepali_address/__init__.py
nepali_address/admin.py
nepali_address/apps.py
nepali_address/forms.py
nepali_address/models.py
nepali_address/tests.py
nepali_address/views.py
nepali_address/fixtures/__init__.py
nepali_address/fixtures/nepali_address.json
nepali_address/migrations/0001_initial.py
nepali_address/migrations/__init__.py
project/__init__.py
project/asgi.py
project/settings.py
project/urls.py
project/wsgi.py
dj_nepali_address-0.2.2.dist-info/LICENSE
dj_nepali_address-0.2.2.dist-info/METADATA
dj_nepali_address-0.2.2.dist-info/WHEEL
dj_nepali_address-0.2.2.dist-info/top_level.txt
dj_nepali_address-0.2.2.dist-info/RECORD
